tensorvision/__init__.py
tensorvision/analyze.py
tensorvision/continue.py
tensorvision/core.py
tensorvision/eval.py
tensorvision/train.py
tensorvision/utils.py
tensorvision-0.1.dev2.data/scripts/tv-analyze
tensorvision-0.1.dev2.data/scripts/tv-continue
tensorvision-0.1.dev2.data/scripts/tv-train
tensorvision-0.1.dev2.dist-info/METADATA
tensorvision-0.1.dev2.dist-info/RECORD
tensorvision-0.1.dev2.dist-info/WHEEL
tensorvision-0.1.dev2.dist-info/top_level.txt
