Metadata-Version: 2.1
Name: tensorvision
Version: 0.1.dev2
Summary: A library to build and train neural networks in with TensorFlow for Computer Vision
Home-page: https://github.com/MarvinTeichmann/TensorVision
Author: Marvin Teichman, Martin Thoma
Author-email: marvin.teichmann@googlemail.com, info@martin-thoma.de
License: MIT
Platform: UNKNOWN
Classifier: Development Status :: 7 - Inactive
Classifier: Intended Audience :: Developers
Classifier: Intended Audience :: Science/Research
Classifier: License :: OSI Approved :: MIT License
Classifier: Programming Language :: Python :: 2.7
Classifier: Programming Language :: Python :: 3
Classifier: Programming Language :: Python :: 3.4
Classifier: Topic :: Scientific/Engineering :: Artificial Intelligence
Provides-Extra: testing
Requires-Dist: numpy
Requires-Dist: scipy
Provides-Extra: testing
Requires-Dist: mock; extra == 'testing'
Requires-Dist: pytest; extra == 'testing'
Requires-Dist: pytest-cov; extra == 'testing'
Requires-Dist: pytest-pep8; extra == 'testing'
